streamlit_canvas_editor/__init__.py
streamlit_canvas_editor/frontend/index.html
streamlit_canvas_editor/frontend/main.js
streamlit_canvas_editor/frontend/streamlit-component-lib.js
streamlit_canvas_editor/frontend/style.css
streamlit_canvas_editor-1.7.0.dist-info/licenses/LICENSE
streamlit_canvas_editor-1.7.0.dist-info/METADATA
streamlit_canvas_editor-1.7.0.dist-info/WHEEL
streamlit_canvas_editor-1.7.0.dist-info/top_level.txt
streamlit_canvas_editor-1.7.0.dist-info/RECORD
